predicatai_core/__init__.py
predicatai_core-0.0.0a1.dist-info/METADATA
predicatai_core-0.0.0a1.dist-info/WHEEL
predicatai_core-0.0.0a1.dist-info/top_level.txt
predicatai_core-0.0.0a1.dist-info/RECORD
