Metadata-Version: 2.4
Name: predicatai-core
Version: 0.0.0a1
Summary: Reserved package name for Predicat (placeholder).
Author-email: Predicat Team <oss@predicat.ai>
License: Apache-2.0
Project-URL: Homepage, https://predicat.ai
Project-URL: Repository, https://github.com/predicatai/predicatai-core
Keywords: predicat,ai,ml,feature-store,pgvector,postgres
Classifier: License :: OSI Approved :: Apache Software License
Classifier: Programming Language :: Python :: 3
Classifier: Programming Language :: Python :: 3 :: Only
Classifier: Development Status :: 1 - Planning
Classifier: Intended Audience :: Developers
Classifier: Topic :: Software Development
Requires-Python: >=3.8
